MANIFEST.in
README.txt
collective.profiler-configure.zcml
setup.py
collective/__init__.py
collective/__init__.pyc
collective.profiler.egg-info/PKG-INFO
collective.profiler.egg-info/SOURCES.txt
collective.profiler.egg-info/dependency_links.txt
collective.profiler.egg-info/entry_points.txt
collective.profiler.egg-info/namespace_packages.txt
collective.profiler.egg-info/not-zip-safe
collective.profiler.egg-info/requires.txt
collective.profiler.egg-info/top_level.txt
collective/profiler/README.txt
collective/profiler/__init__.py
collective/profiler/configure.zcml
collective/profiler/meta.py
collective/profiler/meta.zcml
collective/profiler/tests.py
collective/profiler/zope2.py
docs/HISTORY.txt