Metadata-Version: 1.0
Name: collective.profiler
Version: 0.3
Summary: 'Declare function for profiling in zcml and profileit'
Home-page: https://github.com/collective/collective.profiler
Author: yboussard
Author-email: yboussard@alterway.fr
License: GPL
Platform: UNKNOWN
Classifier: Programming Language :: Python
Classifier: Framework :: Zope2
Classifier: Framework :: Zope3
Classifier: Framework :: Plone
Classifier: Intended Audience :: Developers
Classifier: Topic :: Utilities
